{
  "Version": 3,
  "Meta": {
    "Duration": 1.0,
    "Fps": 60.0,
    "Loop": true,
    "AreBeziersRestricted": true,
    "CurveCount": 44,
    "TotalSegmentCount": 111,
    "TotalPointCount": 197,
    "UserDataCount": 0,
    "TotalUserDataSize": 0
  },
  "Curves": [
    {
      "Target": "Parameter",
      "Id": "ParamAngleX",
      "Segments": [
        0,
        2,
        0,
        0.333,
        4.08,
        1,
        0.444,
        4.08,
        0.556,
        -8.531,
        0.667,
        -9.88,
        1,
        0.778,
        -11.229,
        0.889,
        -11,
        1,
        -11
      ]
    },
    {
      "Target": "Parameter",
      "Id": "ParamAngleY",
      "Segments": [
        0,
        -21,
        0,
        0.333,
        -23.718,
        0,
        0.583,
        10.017,
        0,
        1,
        8
      ]
    },
    {
      "Target": "Parameter",
      "Id": "ParamAngleZ",
      "Segments": [
        0,
        -2,
        0,
        0.35,
        7,
        1,
        0.461,
        7,
        0.572,
        -5.698,
        0.683,
        -7,
        1,
        0.789,
        -8.237,
        0.894,
        -8,
        1,
        -8
      ]
    },
    {
      "Target": "Parameter",
      "Id": "ParamEyeBallX",
      "Segments": [
        0,
        -0.2,
        1,
        0.111,
        -0.2,
        0.222,
        -0.2,
        0.333,
        -0.081,
        1,
        0.555,
        0.156,
        0.778,
        0.392,
        1,
        0.392
      ]
    },
    {
      "Target": "Parameter",
      "Id": "ParamEyeBallY",
      "Segments": [
        0,
        0.3,
        1,
        0.111,
        0.3,
        0.222,
        0.306,
        0.333,
        0.25,
        1,
        0.416,
        0.208,
        0.5,
        -0.353,
        0.583,
        -0.353,
        0,
        1,
        -0.28
      ]
    },
    {
      "Target": "Parameter",
      "Id": "ParamBodyAngleX",
      "Segments": [
        0,
        -4,
        0,
        0.317,
        0,
        0,
        1,
        -2
      ]
    },
    {
      "Target": "Parameter",
      "Id": "ParamBodyAngleY",
      "Segments": [
        0,
        0,
        0,
        0.317,
        -2,
        0,
        0.483,
        3.34,
        0,
        0.817,
        1.567,
        0,
        1,
        2
      ]
    },
    {
      "Target": "Parameter",
      "Id": "ParamBodyAngleZ",
      "Segments": [
        0,
        -2,
        0,
        0.333,
        2.264,
        1,
        0.444,
        2.264,
        0.556,
        0.881,
        0.667,
        -0.028,
        1,
        0.778,
        -0.937,
        0.889,
        -1,
        1,
        -1
      ]
    },
    {
      "Target": "Parameter",
      "Id": "ParamBodyWeight",
      "Segments": [
        0,
        7,
        0,
        0.333,
        3,
        0,
        1,
        9
      ]
    },
    {
      "Target": "Parameter",
      "Id": "ParamBodyFrontAndBack",
      "Segments": [
        0,
        2,
        0,
        0.35,
        22,
        0,
        0.683,
        -9,
        0,
        1,
        -8
      ]
    },
    {
      "Target": "Parameter",
      "Id": "ParamLeftShoulderUp",
      "Segments": [
        0,
        10,
        2,
        0.317,
        10,
        0,
        0.567,
        21,
        0,
        1,
        10
      ]
    },
    {
      "Target": "Parameter",
      "Id": "ParamArmLUp",
      "Segments": [
        0,
        -1,
        1,
        0.106,
        -1,
        0.211,
        -1,
        0.317,
        -0.704,
        1,
        0.372,
        -0.548,
        0.428,
        5.062,
        0.483,
        5.062,
        1,
        0.539,
        5.062,
        0.594,
        3.418,
        0.65,
        3.288,
        1,
        0.767,
        3.015,
        0.883,
        3,
        1,
        3
      ]
    },
    {
      "Target": "Parameter",
      "Id": "ParamArmLFrontBack",
      "Segments": [
        0,
        9,
        0,
        0.317,
        28,
        0,
        1,
        12
      ]
    },
    {
      "Target": "Parameter",
      "Id": "ParamLeftArmRotation",
      "Segments": [
        0,
        -3,
        2,
        0.333,
        -3,
        0,
        0.667,
        5.366,
        0,
        1,
        5
      ]
    },
    {
      "Target": "Parameter",
      "Id": "ParamLeftArmFrontRotation",
      "Segments": [
        0,
        30,
        1,
        0.111,
        30,
        0.222,
        29.93,
        0.333,
        29,
        1,
        0.394,
        28.489,
        0.456,
        24.074,
        0.517,
        23.322,
        1,
        0.567,
        22.707,
        0.617,
        22.348,
        0.667,
        22.249,
        1,
        0.778,
        22.029,
        0.889,
        22,
        1,
        22
      ]
    },
    {
      "Target": "Parameter",
      "Id": "ParamLeftWristRotation",
      "Segments": [
        0,
        56,
        1,
        0.111,
        56,
        0.222,
        56.449,
        0.333,
        58,
        1,
        0.361,
        58.388,
        0.389,
        59.792,
        0.417,
        59.792,
        2,
        0.433,
        -58.207,
        0,
        0.683,
        -51.483,
        1,
        0.722,
        -51.483,
        0.761,
        -52.886,
        0.8,
        -53.276,
        1,
        0.867,
        -53.945,
        0.933,
        -54,
        1,
        -54
      ]
    },
    {
      "Target": "Parameter",
      "Id": "ParamRightShoulderUp",
      "Segments": [
        0,
        9,
        0,
        0.317,
        8.897,
        0,
        0.567,
        14.798,
        0,
        1,
        6
      ]
    },
    {
      "Target": "Parameter",
      "Id": "ParamArmRUp",
      "Segments": [
        0,
        -2,
        1,
        0.106,
        -2,
        0.211,
        -1.871,
        0.317,
        -0.36,
        1,
        0.367,
        0.356,
        0.417,
        7.853,
        0.467,
        7.853,
        1,
        0.528,
        7.853,
        0.589,
        2.484,
        0.65,
        2.318,
        1,
        0.767,
        2.001,
        0.883,
        2,
        1,
        2
      ]
    },
    {
      "Target": "Parameter",
      "Id": "ParamArmRFrontBack",
      "Segments": [
        0,
        -2,
        0,
        1,
        12
      ]
    },
    {
      "Target": "Parameter",
      "Id": "ParamRightArmRotation",
      "Segments": [
        0,
        -3.12,
        0,
        0.333,
        -4.6,
        1,
        0.378,
        -4.6,
        0.422,
        -1.347,
        0.467,
        1.512,
        1,
        0.484,
        2.584,
        0.5,
        2.615,
        0.517,
        3.4,
        2,
        0.533,
        9.82,
        1,
        0.539,
        9.82,
        0.544,
        9.259,
        0.55,
        8.979,
        1,
        0.589,
        7.02,
        0.628,
        4.16,
        0.667,
        3.462,
        1,
        0.706,
        2.764,
        0.744,
        2.222,
        0.783,
        2.146,
        1,
        0.855,
        2.005,
        0.928,
        2,
        1,
        2
      ]
    },
    {
      "Target": "Parameter",
      "Id": "ParamRightArmFrontRotation",
      "Segments": [
        0,
        0,
        1,
        0.111,
        0,
        0.222,
        0.027,
        0.333,
        1,
        1,
        0.394,
        1.535,
        0.456,
        8.981,
        0.517,
        13.2,
        2,
        0.533,
        15.3,
        1,
        0.578,
        20.512,
        0.622,
        23.052,
        0.667,
        23.052,
        1,
        0.706,
        23.052,
        0.744,
        22.283,
        0.783,
        22.186,
        1,
        0.855,
        22.007,
        0.928,
        22,
        1,
        22
      ]
    },
    {
      "Target": "Parameter",
      "Id": "ParamRightWristRotation",
      "Segments": [
        0,
        -5.54,
        0,
        0.333,
        -12,
        0,
        0.517,
        -5.5,
        2,
        0.533,
        -50.29,
        0,
        0.683,
        -49.215,
        1,
        0.722,
        -49.215,
        0.761,
        -50.84,
        0.8,
        -50.9,
        1,
        0.867,
        -51.003,
        0.933,
        -51,
        1,
        -51
      ]
    },
    {
      "Target": "Parameter",
      "Id": "ParamRightHandGrip",
      "Segments": [
        0,
        1,
        0,
        1,
        0
      ]
    },
    {
      "Target": "Parameter",
      "Id": "ParamRightArmOrder",
      "Segments": [
        0,
        0,
        2,
        0.333,
        0,
        0,
        0.35,
        1,
        2,
        1,
        1
      ]
    },
    {
      "Target": "Parameter",
      "Id": "ParamWingBodyLeftOpen",
      "Segments": [
        0,
        1,
        0,
        0.333,
        0.7,
        1,
        0.461,
        0.7,
        0.589,
        0.868,
        0.717,
        0.948,
        1,
        0.811,
        1.007,
        0.906,
        1,
        1,
        1
      ]
    },
    {
      "Target": "Parameter",
      "Id": "ParamWingBodyRightOpen",
      "Segments": [
        0,
        1,
        0,
        0.333,
        0.7,
        1,
        0.461,
        0.7,
        0.589,
        0.864,
        0.717,
        0.946,
        1,
        0.811,
        1.006,
        0.906,
        1,
        1,
        1
      ]
    },
    {
      "Target": "PartOpacity",
      "Id": "PartHandL7",
      "Segments": [
        0,
        1,
        2,
        0.42,
        0,
        2,
        1,
        0
      ]
    },
    {
      "Target": "PartOpacity",
      "Id": "PartHandL6",
      "Segments": [
        0,
        0,
        2,
        0.42,
        1,
        2,
        1,
        1
      ]
    },
    {
      "Target": "PartOpacity",
      "Id": "PartHandL5",
      "Segments": [
        0,
        0,
        2,
        1,
        0
      ]
    },
    {
      "Target": "PartOpacity",
      "Id": "PartHandL4",
      "Segments": [
        0,
        0,
        2,
        1,
        0
      ]
    },
    {
      "Target": "PartOpacity",
      "Id": "PartHandL3",
      "Segments": [
        0,
        0,
        2,
        1,
        0
      ]
    },
    {
      "Target": "PartOpacity",
      "Id": "PartHandL2",
      "Segments": [
        0,
        0,
        2,
        1,
        0
      ]
    },
    {
      "Target": "PartOpacity",
      "Id": "PartHandL1",
      "Segments": [
        0,
        0,
        2,
        1,
        0
      ]
    },
    {
      "Target": "PartOpacity",
      "Id": "PartHandR7",
      "Segments": [
        0,
        0,
        2,
        1,
        0
      ]
    },
    {
      "Target": "PartOpacity",
      "Id": "PartHandR6",
      "Segments": [
        0,
        0,
        2,
        0.53,
        1,
        2,
        1,
        1
      ]
    },
    {
      "Target": "PartOpacity",
      "Id": "PartHandR5",
      "Segments": [
        0,
        0,
        2,
        1,
        0
      ]
    },
    {
      "Target": "PartOpacity",
      "Id": "PartHandR4",
      "Segments": [
        0,
        0,
        2,
        1,
        0
      ]
    },
    {
      "Target": "PartOpacity",
      "Id": "PartHandR3",
      "Segments": [
        0,
        0,
        2,
        1,
        0
      ]
    },
    {
      "Target": "PartOpacity",
      "Id": "PartHandR2",
      "Segments": [
        0,
        0,
        2,
        1,
        0
      ]
    },
    {
      "Target": "PartOpacity",
      "Id": "PartHandR1",
      "Segments": [
        0,
        1,
        2,
        0.53,
        0,
        2,
        1,
        0
      ]
    },
    {
      "Target": "Parameter",
      "Id": "ParamLeftHandGrip",
      "Segments": [
        0,
        0,
        0,
        1,
        0
      ]
    },
    {
      "Target": "Parameter",
      "Id": "ParamLeftArmOrder",
      "Segments": [
        0,
        1,
        0,
        1,
        1
      ]
    },
    {
      "Target": "Parameter",
      "Id": "ParamWingHeadLeftOpen",
      "Segments": [
        0,
        1,
        0,
        1,
        1
      ]
    },
    {
      "Target": "Parameter",
      "Id": "ParamWingHeadRightOpen",
      "Segments": [
        0,
        1,
        0,
        1,
        1
      ]
    }
  ],
  "UserData": []
}