{
  "Version": 3,
  "Meta": {
    "Duration": 1.0,
    "Fps": 60.0,
    "Loop": true,
    "AreBeziersRestricted": true,
    "CurveCount": 46,
    "TotalSegmentCount": 169,
    "TotalPointCount": 227,
    "UserDataCount": 0,
    "TotalUserDataSize": 0
  },
  "Curves": [
    {
      "Target": "Parameter",
      "Id": "ParamAngleX",
      "Segments": [
        0,
        -25,
        1,
        0.089,
        -25,
        0.178,
        -15.151,
        0.267,
        -10,
        1,
        0.317,
        -7.103,
        0.367,
        -7.538,
        0.417,
        -5,
        1,
        0.522,
        0.357,
        0.628,
        6,
        0.733,
        6,
        0,
        0.983,
        4,
        2,
        1,
        4
      ]
    },
    {
      "Target": "Parameter",
      "Id": "ParamAngleY",
      "Segments": [
        0,
        12,
        1,
        0.1,
        12,
        0.2,
        14.795,
        0.3,
        17,
        1,
        0.35,
        18.103,
        0.4,
        18,
        0.45,
        18,
        0,
        0.767,
        -8,
        0,
        0.983,
        -5,
        2,
        1,
        -5
      ]
    },
    {
      "Target": "Parameter",
      "Id": "ParamAngleZ",
      "Segments": [
        0,
        -1,
        1,
        0.111,
        -1,
        0.222,
        0.869,
        0.333,
        3,
        1,
        0.383,
        3.959,
        0.433,
        4,
        0.483,
        4,
        0,
        0.8,
        -16,
        0,
        0.983,
        -14,
        2,
        1,
        -14
      ]
    },
    {
      "Target": "Parameter",
      "Id": "ParamEyeBallX",
      "Segments": [
        0,
        0.8,
        1,
        0.089,
        0.8,
        0.178,
        0.33,
        0.267,
        0.2,
        1,
        0.317,
        0.127,
        0.367,
        0.119,
        0.417,
        0.1,
        1,
        0.522,
        0.06,
        0.628,
        0.037,
        0.733,
        0,
        1,
        0.816,
        -0.029,
        0.9,
        -0.05,
        0.983,
        -0.05,
        2,
        1,
        -0.05
      ]
    },
    {
      "Target": "Parameter",
      "Id": "ParamEyeBallY",
      "Segments": [
        0,
        -0.1,
        0,
        0.3,
        -0.2,
        2,
        0.45,
        -0.2,
        0,
        0.767,
        0.2,
        0,
        0.983,
        0.1,
        2,
        1,
        0.1
      ]
    },
    {
      "Target": "Parameter",
      "Id": "ParamBodyAngleX",
      "Segments": [
        0,
        9,
        1,
        0.078,
        9,
        0.155,
        -2.302,
        0.233,
        -2.8,
        1,
        0.283,
        -3.12,
        0.333,
        -3,
        0.383,
        -3,
        0,
        0.7,
        5,
        0,
        0.983,
        4,
        2,
        1,
        4
      ]
    },
    {
      "Target": "Parameter",
      "Id": "ParamBodyAngleY",
      "Segments": [
        0,
        2,
        1,
        0.083,
        2,
        0.167,
        5.657,
        0.25,
        6.6,
        1,
        0.3,
        7.166,
        0.35,
        7,
        0.4,
        7,
        0,
        0.717,
        -2,
        0,
        0.983,
        2,
        2,
        1,
        2
      ]
    },
    {
      "Target": "Parameter",
      "Id": "ParamBodyAngleZ",
      "Segments": [
        0,
        -4,
        1,
        0.089,
        -4,
        0.178,
        0.242,
        0.267,
        1.5,
        1,
        0.317,
        2.208,
        0.367,
        2,
        0.417,
        2,
        0,
        0.733,
        -3,
        0,
        0.983,
        -2,
        2,
        1,
        -2
      ]
    },
    {
      "Target": "Parameter",
      "Id": "ParamBodyWeight",
      "Segments": [
        0,
        20,
        1,
        0.083,
        20,
        0.167,
        15.989,
        0.25,
        14,
        1,
        0.3,
        12.807,
        0.35,
        13,
        0.4,
        13,
        0,
        0.717,
        17,
        0,
        0.983,
        15,
        2,
        1,
        15
      ]
    },
    {
      "Target": "Parameter",
      "Id": "ParamBodyFrontAndBack",
      "Segments": [
        0,
        -5,
        1,
        0.083,
        -5,
        0.167,
        -15.248,
        0.25,
        -15.8,
        1,
        0.3,
        -16.131,
        0.35,
        -16,
        0.4,
        -16,
        0,
        0.717,
        -8,
        0,
        0.983,
        -10,
        2,
        1,
        -10
      ]
    },
    {
      "Target": "Parameter",
      "Id": "ParamShoulderLUpDown",
      "Segments": [
        0,
        0,
        0,
        0.267,
        5,
        0,
        0.7,
        0,
        2,
        0.983,
        0,
        2,
        1,
        0
      ]
    },
    {
      "Target": "Parameter",
      "Id": "ParamLeftShoulderUp",
      "Segments": [
        0,
        8,
        1,
        0.089,
        8,
        0.178,
        7.214,
        0.267,
        4,
        1,
        0.411,
        -1.222,
        0.556,
        -5,
        0.7,
        -5,
        2,
        0.983,
        -5,
        2,
        1,
        -5
      ]
    },
    {
      "Target": "Parameter",
      "Id": "ParamLArmShoulderRoll",
      "Segments": [
        0,
        0,
        0,
        0.267,
        10,
        0,
        0.7,
        0,
        2,
        0.983,
        0,
        2,
        1,
        0
      ]
    },
    {
      "Target": "Parameter",
      "Id": "ParamLeftArmRotation",
      "Segments": [
        0,
        -2,
        1,
        0.094,
        -2,
        0.189,
        -2.262,
        0.283,
        0,
        1,
        0.428,
        3.46,
        0.572,
        10,
        0.717,
        10,
        2,
        0.983,
        10,
        2,
        1,
        10
      ]
    },
    {
      "Target": "Parameter",
      "Id": "ParamLeftArmFrontRotation",
      "Segments": [
        0,
        2,
        0,
        0.283,
        3,
        0,
        0.717,
        0,
        2,
        0.983,
        0,
        2,
        1,
        0
      ]
    },
    {
      "Target": "Parameter",
      "Id": "ParamLeftSleeveRotation",
      "Segments": [
        0,
        59,
        0,
        0.983,
        60,
        2,
        1,
        60
      ]
    },
    {
      "Target": "Parameter",
      "Id": "ParamLeftWristRotation",
      "Segments": [
        0,
        -4,
        0,
        0.3,
        0,
        2,
        0.733,
        0,
        2,
        0.983,
        0,
        2,
        1,
        0
      ]
    },
    {
      "Target": "Parameter",
      "Id": "ParamShoulderRUpDown",
      "Segments": [
        0,
        0,
        0,
        0.267,
        5,
        0,
        0.7,
        0,
        2,
        0.983,
        0,
        2,
        1,
        0
      ]
    },
    {
      "Target": "Parameter",
      "Id": "ParamRightShoulderUp",
      "Segments": [
        0,
        8,
        1,
        0.089,
        8,
        0.178,
        7.214,
        0.267,
        4,
        1,
        0.411,
        -1.222,
        0.556,
        -5,
        0.7,
        -5,
        2,
        0.983,
        -5,
        2,
        1,
        -5
      ]
    },
    {
      "Target": "Parameter",
      "Id": "ParamRArmShoulderRoll",
      "Segments": [
        0,
        0,
        0,
        0.267,
        10,
        0,
        0.7,
        0,
        2,
        0.983,
        0,
        2,
        1,
        0
      ]
    },
    {
      "Target": "Parameter",
      "Id": "ParamRightArmRotation",
      "Segments": [
        0,
        -5,
        1,
        0.094,
        -5,
        0.189,
        -3.88,
        0.283,
        0,
        1,
        0.428,
        5.934,
        0.572,
        10,
        0.717,
        10,
        2,
        0.983,
        10,
        2,
        1,
        10
      ]
    },
    {
      "Target": "Parameter",
      "Id": "ParamRightArmFrontRotation",
      "Segments": [
        0,
        2,
        0,
        0.283,
        3,
        0,
        0.717,
        0,
        2,
        0.983,
        0,
        2,
        1,
        0
      ]
    },
    {
      "Target": "Parameter",
      "Id": "ParamRightSleeveRotation",
      "Segments": [
        0,
        55,
        0,
        0.983,
        59,
        2,
        1,
        59
      ]
    },
    {
      "Target": "Parameter",
      "Id": "ParamRightWristRotation",
      "Segments": [
        0,
        -2,
        0,
        0.3,
        0,
        2,
        0.733,
        0,
        2,
        0.983,
        0,
        2,
        1,
        0
      ]
    },
    {
      "Target": "Parameter",
      "Id": "ParamRightArmOrder",
      "Segments": [
        0,
        1,
        0,
        0.017,
        0,
        2,
        0.983,
        0,
        2,
        1,
        0
      ]
    },
    {
      "Target": "PartOpacity",
      "Id": "PartLeftHand07",
      "Segments": [
        0,
        0,
        2,
        0.2,
        0,
        2,
        0.42,
        0,
        2,
        0.98,
        0,
        2,
        1,
        0
      ]
    },
    {
      "Target": "PartOpacity",
      "Id": "PartLeftHand06",
      "Segments": [
        0,
        1,
        2,
        0.2,
        0,
        2,
        0.42,
        0,
        2,
        0.98,
        0,
        2,
        1,
        0
      ]
    },
    {
      "Target": "PartOpacity",
      "Id": "PartLeftHand05",
      "Segments": [
        0,
        0,
        2,
        0.2,
        0,
        2,
        0.42,
        1,
        2,
        0.98,
        1,
        2,
        1,
        1
      ]
    },
    {
      "Target": "PartOpacity",
      "Id": "PartLeftHand04",
      "Segments": [
        0,
        0,
        2,
        0.2,
        0,
        2,
        0.42,
        0,
        2,
        0.98,
        0,
        2,
        1,
        0
      ]
    },
    {
      "Target": "PartOpacity",
      "Id": "PartLeftHand03",
      "Segments": [
        0,
        0,
        2,
        0.2,
        0,
        2,
        0.42,
        0,
        2,
        0.98,
        0,
        2,
        1,
        0
      ]
    },
    {
      "Target": "PartOpacity",
      "Id": "PartLeftHand02",
      "Segments": [
        0,
        0,
        2,
        0.2,
        0,
        2,
        0.42,
        0,
        2,
        0.98,
        0,
        2,
        1,
        0
      ]
    },
    {
      "Target": "PartOpacity",
      "Id": "PartLeftHand01",
      "Segments": [
        0,
        0,
        2,
        0.2,
        1,
        2,
        0.42,
        0,
        2,
        0.98,
        0,
        2,
        1,
        0
      ]
    },
    {
      "Target": "PartOpacity",
      "Id": "PartRightHand07",
      "Segments": [
        0,
        0,
        2,
        0.2,
        0,
        2,
        0.42,
        0,
        2,
        0.98,
        0,
        2,
        1,
        0
      ]
    },
    {
      "Target": "PartOpacity",
      "Id": "PartRightHand06",
      "Segments": [
        0,
        1,
        2,
        0.2,
        0,
        2,
        0.42,
        0,
        2,
        0.98,
        0,
        2,
        1,
        0
      ]
    },
    {
      "Target": "PartOpacity",
      "Id": "PartRightHand05",
      "Segments": [
        0,
        0,
        2,
        0.2,
        0,
        2,
        0.42,
        0,
        2,
        0.98,
        0,
        2,
        1,
        0
      ]
    },
    {
      "Target": "PartOpacity",
      "Id": "PartRightHand04",
      "Segments": [
        0,
        0,
        2,
        0.2,
        0,
        2,
        0.42,
        0,
        2,
        0.98,
        0,
        2,
        1,
        0
      ]
    },
    {
      "Target": "PartOpacity",
      "Id": "PartRightHand03",
      "Segments": [
        0,
        0,
        2,
        0.2,
        0,
        2,
        0.42,
        0,
        2,
        0.98,
        0,
        2,
        1,
        0
      ]
    },
    {
      "Target": "PartOpacity",
      "Id": "PartRightHand02",
      "Segments": [
        0,
        0,
        2,
        0.2,
        0,
        2,
        0.42,
        1,
        2,
        0.98,
        1,
        2,
        1,
        1
      ]
    },
    {
      "Target": "PartOpacity",
      "Id": "PartRightHand01",
      "Segments": [
        0,
        0,
        2,
        0.2,
        1,
        2,
        0.42,
        0,
        2,
        0.98,
        0,
        2,
        1,
        0
      ]
    },
    {
      "Target": "Parameter",
      "Id": "ParamLeftSleeveFrontRotation",
      "Segments": [
        0,
        30,
        0,
        1,
        30
      ]
    },
    {
      "Target": "Parameter",
      "Id": "ParamLeftSleeveRotationZ",
      "Segments": [
        0,
        0,
        0,
        1,
        0
      ]
    },
    {
      "Target": "Parameter",
      "Id": "ParamLeftArmOrder",
      "Segments": [
        0,
        0,
        0,
        1,
        0
      ]
    },
    {
      "Target": "Parameter",
      "Id": "ParamLeftHandGrip",
      "Segments": [
        0,
        1,
        0,
        1,
        1
      ]
    },
    {
      "Target": "Parameter",
      "Id": "ParamRightSleeveFrontRotation",
      "Segments": [
        0,
        30,
        0,
        1,
        30
      ]
    },
    {
      "Target": "Parameter",
      "Id": "ParamRightSleeveRotationZ",
      "Segments": [
        0,
        0,
        0,
        1,
        0
      ]
    },
    {
      "Target": "Parameter",
      "Id": "ParamRightHandGrip",
      "Segments": [
        0,
        1,
        0,
        1,
        1
      ]
    }
  ],
  "UserData": []
}