{
  "Version": 3,
  "Meta": {
    "Duration": 1.0,
    "Fps": 60.0,
    "Loop": true,
    "AreBeziersRestricted": true,
    "CurveCount": 32,
    "TotalSegmentCount": 99,
    "TotalPointCount": 195,
    "UserDataCount": 0,
    "TotalUserDataSize": 0
  },
  "Curves": [
    {
      "Target": "Parameter",
      "Id": "ParamAngleX",
      "Segments": [
        0,
        5,
        1,
        0.061,
        5,
        0.122,
        4.961,
        0.183,
        7.369,
        1,
        0.316,
        12.623,
        0.45,
        17.96,
        0.583,
        17.96,
        1,
        0.694,
        17.96,
        0.806,
        15.443,
        0.917,
        11.9,
        1,
        0.945,
        11.014,
        0.972,
        11,
        1,
        11
      ]
    },
    {
      "Target": "Parameter",
      "Id": "ParamAngleY",
      "Segments": [
        0,
        5,
        0,
        0.217,
        1,
        0,
        0.583,
        14,
        0,
        1,
        -5
      ]
    },
    {
      "Target": "Parameter",
      "Id": "ParamAngleZ",
      "Segments": [
        0,
        21,
        1,
        0.061,
        21,
        0.122,
        21.475,
        0.183,
        19,
        1,
        0.339,
        12.701,
        0.494,
        4,
        0.65,
        4,
        1,
        0.717,
        4,
        0.783,
        9.559,
        0.85,
        11.072,
        1,
        0.9,
        12.206,
        0.95,
        12,
        1,
        12
      ]
    },
    {
      "Target": "Parameter",
      "Id": "ParamEyeBallX",
      "Segments": [
        0,
        -0.1,
        1,
        0.072,
        -0.1,
        0.145,
        -0.162,
        0.217,
        -0.186,
        1,
        0.339,
        -0.227,
        0.461,
        -0.232,
        0.583,
        -0.232,
        0,
        0.917,
        -0.128,
        0,
        1,
        -0.2
      ]
    },
    {
      "Target": "Parameter",
      "Id": "ParamEyeBallY",
      "Segments": [
        0,
        -0.3,
        0,
        0.217,
        -0.184,
        0,
        0.583,
        -0.3,
        0,
        1,
        0.022
      ]
    },
    {
      "Target": "Parameter",
      "Id": "ParamBodyAngleX",
      "Segments": [
        0,
        -5,
        1,
        0.089,
        -5,
        0.178,
        -3.283,
        0.267,
        -1.118,
        1,
        0.367,
        1.317,
        0.467,
        3.727,
        0.567,
        5.271,
        1,
        0.617,
        6.044,
        0.667,
        6.023,
        0.717,
        6.023,
        0,
        1,
        5
      ]
    },
    {
      "Target": "Parameter",
      "Id": "ParamBodyAngleY",
      "Segments": [
        0,
        0,
        0,
        0.267,
        -1,
        1,
        0.322,
        -1,
        0.378,
        0.486,
        0.433,
        0.956,
        1,
        0.5,
        1.521,
        0.566,
        1.511,
        0.633,
        1.511,
        1,
        0.711,
        1.511,
        0.789,
        -0.519,
        0.867,
        -0.871,
        1,
        0.911,
        -1.073,
        0.956,
        -1,
        1,
        -1
      ]
    },
    {
      "Target": "Parameter",
      "Id": "ParamBodyAngleZ",
      "Segments": [
        0,
        -3,
        0,
        0.2,
        1,
        1,
        0.244,
        1,
        0.289,
        1.028,
        0.333,
        0.415,
        1,
        0.389,
        -0.352,
        0.444,
        -2.993,
        0.5,
        -3.902,
        1,
        0.544,
        -4.629,
        0.589,
        -4.653,
        0.633,
        -4.653,
        0,
        1,
        -4
      ]
    },
    {
      "Target": "Parameter",
      "Id": "ParamBodyFrontAndBack",
      "Segments": [
        0,
        -2,
        0,
        0.217,
        0,
        1,
        0.284,
        0,
        0.35,
        -1.961,
        0.417,
        -2.569,
        1,
        0.472,
        -3.075,
        0.528,
        -3,
        0.583,
        -3,
        0,
        1,
        -2
      ]
    },
    {
      "Target": "Parameter",
      "Id": "ParamBodyWeight",
      "Segments": [
        0,
        9,
        0,
        0.267,
        4.431,
        0,
        0.583,
        17.968,
        1,
        0.666,
        17.968,
        0.75,
        11.826,
        0.833,
        9.375,
        1,
        0.889,
        7.741,
        0.944,
        8,
        1,
        8
      ]
    },
    {
      "Target": "Parameter",
      "Id": "ParamLeftShoulderUpDown",
      "Segments": [
        0,
        0,
        0,
        1,
        -8
      ]
    },
    {
      "Target": "Parameter",
      "Id": "ParamLeftArmShoulderUp",
      "Segments": [
        0,
        15,
        0,
        0.2,
        13.157,
        1,
        0.256,
        13.157,
        0.311,
        19.946,
        0.367,
        22.436,
        1,
        0.411,
        24.427,
        0.456,
        24.252,
        0.5,
        24.252,
        1,
        0.561,
        24.252,
        0.622,
        21.825,
        0.683,
        16.899,
        1,
        0.744,
        11.974,
        0.806,
        4.915,
        0.867,
        2.052,
        1,
        0.911,
        -0.03,
        0.956,
        0,
        1,
        0
      ]
    },
    {
      "Target": "Parameter",
      "Id": "ParamLeftArmShoulderFrontAndBack",
      "Segments": [
        0,
        10,
        0,
        1,
        0
      ]
    },
    {
      "Target": "Parameter",
      "Id": "ParamLeftArmRotation",
      "Segments": [
        0,
        -54,
        1,
        0.056,
        -54,
        0.111,
        -55.224,
        0.167,
        -58.208,
        1,
        0.172,
        -58.506,
        0.178,
        -60,
        0.183,
        -60,
        2,
        0.2,
        58.2,
        1,
        0.206,
        58.2,
        0.211,
        57.559,
        0.217,
        56.215,
        1,
        0.284,
        40.093,
        0.35,
        18.866,
        0.417,
        7.785,
        1,
        0.461,
        0.398,
        0.506,
        0,
        0.55,
        0,
        2,
        0.65,
        0,
        0,
        0.783,
        -3.509,
        0,
        1,
        0
      ]
    },
    {
      "Target": "Parameter",
      "Id": "ParamLeftArmFrontRotation",
      "Segments": [
        0,
        4,
        1,
        0.061,
        4,
        0.122,
        4.026,
        0.183,
        4.251,
        1,
        0.205,
        4.333,
        0.228,
        10.791,
        0.25,
        12.572,
        1,
        0.267,
        13.907,
        0.283,
        13.98,
        0.3,
        13.98,
        1,
        0.361,
        13.98,
        0.422,
        5.713,
        0.483,
        4.071,
        1,
        0.555,
        2.131,
        0.628,
        0.618,
        0.7,
        0.353,
        1,
        0.8,
        -0.015,
        0.9,
        0,
        1,
        0
      ]
    },
    {
      "Target": "Parameter",
      "Id": "ParamLeftArmOrder",
      "Segments": [
        0,
        1,
        0,
        1,
        0
      ]
    },
    {
      "Target": "Parameter",
      "Id": "ParamLeftWristRotation",
      "Segments": [
        0,
        -11,
        0,
        0.183,
        5.634,
        0,
        0.717,
        -11.216,
        0,
        1,
        0
      ]
    },
    {
      "Target": "Parameter",
      "Id": "ParamRightShoulderUpDown",
      "Segments": [
        0,
        10,
        0,
        1,
        -8
      ]
    },
    {
      "Target": "Parameter",
      "Id": "ParamRightArmShoulderUp",
      "Segments": [
        0,
        1,
        1,
        0.083,
        1,
        0.167,
        2.998,
        0.25,
        5.437,
        1,
        0.333,
        7.876,
        0.417,
        8.56,
        0.5,
        8.56,
        0,
        0.85,
        -1.969,
        0,
        1,
        -1.2
      ]
    },
    {
      "Target": "Parameter",
      "Id": "ParamRightArmRotation",
      "Segments": [
        0,
        -3,
        0,
        0.217,
        0.243,
        0,
        0.517,
        -1.733,
        0,
        0.883,
        2.194,
        0,
        1,
        2
      ]
    },
    {
      "Target": "Parameter",
      "Id": "ParamRightArmFrontRotation",
      "Segments": [
        0,
        4.01,
        1,
        0.061,
        4.01,
        0.122,
        3.633,
        0.183,
        3.402,
        1,
        0.278,
        3.044,
        0.372,
        2.954,
        0.467,
        2.562,
        1,
        0.55,
        2.216,
        0.634,
        0.795,
        0.717,
        0.654,
        1,
        0.811,
        0.494,
        0.906,
        0.512,
        1,
        0.512
      ]
    },
    {
      "Target": "Parameter",
      "Id": "ParamCanonRotation",
      "Segments": [
        0,
        0,
        0,
        0.233,
        -1,
        0,
        0.583,
        10.193,
        1,
        0.661,
        10.193,
        0.739,
        3.474,
        0.817,
        1.399,
        1,
        0.878,
        -0.232,
        0.939,
        0,
        1,
        0
      ]
    },
    {
      "Target": "Parameter",
      "Id": "ParamRightArmOrder",
      "Segments": [
        0,
        1,
        2,
        0.5,
        1,
        2,
        0.517,
        0,
        2,
        1,
        0
      ]
    },
    {
      "Target": "PartOpacity",
      "Id": "PartLeftHand01",
      "Segments": [
        0,
        0,
        2,
        0.33,
        1,
        2,
        1,
        0
      ]
    },
    {
      "Target": "PartOpacity",
      "Id": "PartLeftHand02",
      "Segments": [
        0,
        0,
        2,
        1,
        1
      ]
    },
    {
      "Target": "PartOpacity",
      "Id": "PartLeftHand03",
      "Segments": [
        0,
        1,
        2,
        0.33,
        0,
        2,
        1,
        0
      ]
    },
    {
      "Target": "PartOpacity",
      "Id": "PartLeftHand04",
      "Segments": [
        0,
        0,
        2,
        1,
        0
      ]
    },
    {
      "Target": "PartOpacity",
      "Id": "PartLeftHand05",
      "Segments": [
        0,
        0,
        2,
        1,
        0
      ]
    },
    {
      "Target": "PartOpacity",
      "Id": "PartLeftHand06",
      "Segments": [
        0,
        0,
        2,
        1,
        0
      ]
    },
    {
      "Target": "PartOpacity",
      "Id": "PartLeftHand07",
      "Segments": [
        0,
        0,
        2,
        1,
        0
      ]
    },
    {
      "Target": "Parameter",
      "Id": "ParamLeftHandGrip",
      "Segments": [
        0,
        0,
        0,
        1,
        0
      ]
    },
    {
      "Target": "Parameter",
      "Id": "ParamRightArmShoulderFrontAndBack",
      "Segments": [
        0,
        -10,
        0,
        1,
        -10
      ]
    }
  ],
  "UserData": []
}